pinpayments/__init__.py
pinpayments/constants.py
pinpayments/exceptions.py
pinpayments/pinpayments.py
pinpayments-0.1.1.dist-info/DESCRIPTION.rst
pinpayments-0.1.1.dist-info/METADATA
pinpayments-0.1.1.dist-info/RECORD
pinpayments-0.1.1.dist-info/WHEEL
pinpayments-0.1.1.dist-info/metadata.json
pinpayments-0.1.1.dist-info/top_level.txt
